dex2call/__init__.py
dex2call/cli.py
dex2call-0.3.0.dist-info/METADATA
dex2call-0.3.0.dist-info/RECORD
dex2call-0.3.0.dist-info/WHEEL
dex2call-0.3.0.dist-info/entry_points.txt
dex2call-0.3.0.dist-info/top_level.txt
