Metadata-Version: 2.1
Name: dex2call
Version: 0.3.0
Summary: A simple module to get calls to android.jar from the bytecode
Home-page: https://github.com/KuroAku/dex2call
Author: Daniel Domínguez
Author-email: daniel.dominguez@imdea.org
License: LICENSE
Platform: UNKNOWN
Requires-Dist: Click
Requires-Dist: r2pipe
Requires-Dist: androguard
